{"__type__":"sp.SkeletonData","_name":"cowboy cmc3","skeletonJsonStr":"{\r\n\"skeleton\": { \"hash\": \"ylgk/0WvXHjNdESHLRJqUtGulxI\", \"spine\": \"3.6.52\", \"width\": 377.01, \"height\": 553, \"images\": \"./images/cowboy cmc/\" },\r\n\"bones\": [\r\n\t{ \"name\": \"root\" },\r\n\t{ \"name\": \"bone\", \"parent\": \"root\", \"x\": 33.09, \"y\": 163.96 },\r\n\t{ \"name\": \"bone2\", \"parent\": \"bone\", \"length\": 134.98, \"rotation\": 89.04, \"x\": -5.28, \"y\": 36.83 },\r\n\t{ \"name\": \"bone3\", \"parent\": \"bone2\", \"length\": 79.17, \"rotation\": 0.41, \"x\": 134.98 },\r\n\t{ \"name\": \"bone4\", \"parent\": \"bone3\", \"length\": 175.24, \"rotation\": 0.55, \"x\": 78.81, \"y\": -1.05 },\r\n\t{ \"name\": \"bone5\", \"parent\": \"bone4\", \"length\": 62.57, \"rotation\": 164.98, \"x\": 159.07, \"y\": 32.16 },\r\n\t{ \"name\": \"bone6\", \"parent\": \"bone4\", \"length\": 60.92, \"rotation\": -145.35, \"x\": 77.26, \"y\": -49.65 },\r\n\t{ \"name\": \"bone7\", \"parent\": \"bone4\", \"length\": 61, \"rotation\": 171.67, \"x\": 42.28, \"y\": 46.33 },\r\n\t{ \"name\": \"bone8\", \"parent\": \"bone3\", \"x\": 2.78, \"y\": -1.31 },\r\n\t{ \"name\": \"bone9\", \"parent\": \"bone4\", \"x\": 93.22, \"y\": -39.79 },\r\n\t{ \"name\": \"bone10\", \"parent\": \"bone4\", \"x\": 133.48, \"y\": 7.26 },\r\n\t{ \"name\": \"bone11\", \"parent\": \"bone4\", \"x\": 144.63, \"y\": -36.88 },\r\n\t{ \"name\": \"bone12\", \"parent\": \"bone3\", \"length\": 91.67, \"rotation\": 160.22, \"x\": 35.73, \"y\": 89.9 },\r\n\t{ \"name\": \"bone13\", \"parent\": \"bone\", \"length\": 74.46, \"rotation\": 91.97, \"x\": -17.51, \"y\": 476.98 },\r\n\t{ \"name\": \"bone14\", \"parent\": \"root\", \"x\": 29.99, \"y\": 166.11 },\r\n\t{ \"name\": \"bone15\", \"parent\": \"bone14\", \"length\": 123.76, \"rotation\": 90.41, \"x\": 12.6, \"y\": 20.45 },\r\n\t{ \"name\": \"bone16\", \"parent\": \"bone15\", \"length\": 144.41, \"rotation\": -7.8, \"x\": 123.76 },\r\n\t{ \"name\": \"bone17\", \"parent\": \"bone16\", \"length\": 141.52, \"rotation\": 11.35, \"x\": 143.09, \"y\": -1.01 },\r\n\t{ \"name\": \"bone18\", \"parent\": \"bone16\", \"x\": 32.44, \"y\": 11.42 },\r\n\t{ \"name\": \"bone19\", \"parent\": \"bone16\", \"length\": 203.68, \"rotation\": 156.39, \"x\": 93.1, \"y\": 49.9 },\r\n\t{ \"name\": \"bone20\", \"parent\": \"bone19\", \"length\": 206.98, \"rotation\": -149.2, \"x\": 207.9, \"y\": -7.07 },\r\n\t{ \"name\": \"bone21\", \"parent\": \"bone17\", \"length\": 43.99, \"rotation\": 88.68, \"x\": 184.4, \"y\": 1.42 },\r\n\t{ \"name\": \"bone22\", \"parent\": \"bone21\", \"length\": 31.78, \"rotation\": 26.65, \"x\": 43.99 },\r\n\t{ \"name\": \"bone23\", \"parent\": \"bone22\", \"length\": 28.72, \"rotation\": 34.14, \"x\": 31.78 },\r\n\t{ \"name\": \"bone24\", \"parent\": \"bone23\", \"length\": 36.53, \"rotation\": 24.44, \"x\": 28.72 },\r\n\t{ \"name\": \"bone25\", \"parent\": \"bone17\", \"x\": 80.83, \"y\": 32.31 },\r\n\t{ \"name\": \"bone26\", \"parent\": \"bone17\", \"x\": 78.56, \"y\": -10.23 },\r\n\t{ \"name\": \"bone27\", \"parent\": \"bone17\", \"x\": 31.11, \"y\": 18.81 },\r\n\t{ \"name\": \"bone28\", \"parent\": \"bone14\", \"x\": 3.3, \"y\": -4.63 },\r\n\t{ \"name\": \"bone29\", \"parent\": \"bone28\", \"length\": 212.35, \"rotation\": 90, \"x\": -54.74, \"y\": 25.56 },\r\n\t{ \"name\": \"bone30\", \"parent\": \"bone29\", \"length\": 260.85, \"rotation\": -122.01, \"x\": 179.17, \"y\": 67.47 },\r\n\t{ \"name\": \"bone31\", \"parent\": \"bone30\", \"length\": 253.36, \"rotation\": 123.51, \"x\": 253.58, \"y\": 3.28 },\r\n\t{ \"name\": \"bone32\", \"parent\": \"bone29\", \"length\": 209.66, \"rotation\": -2.65, \"x\": 233.48, \"y\": 0.67 },\r\n\t{ \"name\": \"bone33\", \"parent\": \"bone32\", \"x\": 131.42, \"y\": -27.56 },\r\n\t{ \"name\": \"bone34\", \"parent\": \"bone33\", \"x\": -6.29, \"y\": -49.68 },\r\n\t{ \"name\": \"bone35\", \"parent\": \"bone32\", \"x\": 73.2, \"y\": -22.37 },\r\n\t{ \"name\": \"bone36\", \"parent\": \"bone14\", \"length\": 94.59, \"rotation\": 90, \"x\": -19.62, \"y\": 477.14 },\r\n\t{ \"name\": \"bone37\", \"parent\": \"bone28\", \"length\": 68.17, \"rotation\": 91.17, \"x\": -4.32, \"y\": 477.59 }\r\n],\r\n\"slots\": [\r\n\t{ \"name\": \"cut\", \"bone\": \"root\", \"attachment\": \"cut\" },\r\n\t{ \"name\": \"co3 cowboy\", \"bone\": \"bone28\", \"attachment\": \"co3 cowboy\" },\r\n\t{ \"name\": \"co3 body\", \"bone\": \"bone29\", \"attachment\": \"co3 body\" },\r\n\t{ \"name\": \"co3 head\", \"bone\": \"bone32\", \"attachment\": \"co3 head\" },\r\n\t{ \"name\": \"co3 mat2\", \"bone\": \"bone34\", \"attachment\": \"co3 mat2\" },\r\n\t{ \"name\": \"co3 mat1\", \"bone\": \"bone33\", \"attachment\": \"co3 mat1\" },\r\n\t{ \"name\": \"co3 omlua\", \"bone\": \"bone35\", \"attachment\": \"co3 omlua\" },\r\n\t{ \"name\": \"co3 tay1\", \"bone\": \"bone30\", \"attachment\": \"co3 tay1\" },\r\n\t{ \"name\": \"co3 tay2\", \"bone\": \"bone31\", \"attachment\": \"co3 tay2\" },\r\n\t{ \"name\": \"co3 Layer 2 copy 3\", \"bone\": \"bone28\", \"attachment\": \"co3 Layer 2 copy 3\" },\r\n\t{ \"name\": \"co3 shape\", \"bone\": \"bone28\", \"attachment\": \"co3 shape\" },\r\n\t{ \"name\": \"co3 COWBOY 3\", \"bone\": \"bone37\", \"attachment\": \"co3 COWBOY 3\" }\r\n],\r\n\"skins\": {\r\n\t\"default\": {\r\n\t\t\"co3 COWBOY 3\": {\r\n\t\t\t\"co3 COWBOY 3\": { \"x\": 35.32, \"y\": -6.66, \"rotation\": -91.17, \"width\": 197, \"height\": 80 }\r\n\t\t},\r\n\t\t\"co3 Layer 2 copy 3\": {\r\n\t\t\t\"co3 Layer 2 copy 3\": { \"x\": -2.88, \"y\": 291.54, \"width\": 318, \"height\": 553 }\r\n\t\t},\r\n\t\t\"co3 body\": {\r\n\t\t\t\"co3 body\": { \"x\": 161.48, \"y\": -5.85, \"rotation\": -90, \"width\": 336, \"height\": 322 }\r\n\t\t},\r\n\t\t\"co3 cowboy\": {\r\n\t\t\t\"co3 cowboy\": { \"x\": 1.12, \"y\": 300.54, \"width\": 318, \"height\": 529 }\r\n\t\t},\r\n\t\t\"co3 head\": {\r\n\t\t\t\"co3 head\": { \"x\": 105.42, \"y\": -39.2, \"rotation\": -87.35, \"width\": 289, \"height\": 267 }\r\n\t\t},\r\n\t\t\"co3 mat1\": {\r\n\t\t\t\"co3 mat1\": { \"x\": -0.55, \"y\": 1.04, \"rotation\": -87.35, \"width\": 38, \"height\": 21 }\r\n\t\t},\r\n\t\t\"co3 mat2\": {\r\n\t\t\t\"co3 mat2\": { \"x\": 3.06, \"y\": 0.54, \"rotation\": -87.35, \"width\": 24, \"height\": 19 }\r\n\t\t},\r\n\t\t\"co3 omlua\": {\r\n\t\t\t\"co3 omlua\": { \"x\": -1.14, \"y\": 1.15, \"rotation\": -87.35, \"width\": 12, \"height\": 12 }\r\n\t\t},\r\n\t\t\"co3 shape\": {\r\n\t\t\t\"co3 shape\": { \"x\": 1.12, \"y\": 133.54, \"width\": 220, \"height\": 77 }\r\n\t\t},\r\n\t\t\"co3 tay1\": {\r\n\t\t\t\"co3 tay1\": { \"x\": 119.94, \"y\": 8.7, \"rotation\": 32.01, \"width\": 264, \"height\": 225 }\r\n\t\t},\r\n\t\t\"co3 tay2\": {\r\n\t\t\t\"co3 tay2\": { \"x\": 187.2, \"y\": 8.06, \"rotation\": -91.5, \"width\": 111, \"height\": 424 }\r\n\t\t},\r\n\t\t\"cut\": {\r\n\t\t\t\"cut\": {\r\n\t\t\t\t\"type\": \"clipping\",\r\n\t\t\t\t\"end\": \"co3 tay2\",\r\n\t\t\t\t\"vertexCount\": 8,\r\n\t\t\t\t\"vertices\": [ -92.79, 203.54, 123.84, 203.36, 157.39, 229.59, 157.2, 679.76, 130.06, 705.46, -96.85, 705.82, -113.3, 682.8, -115.76, 237.44 ],\r\n\t\t\t\t\"color\": \"ce3a3aff\"\r\n\t\t\t}\r\n\t\t}\r\n\t}\r\n},\r\n\"animations\": {\r\n\t\"co3\": {\r\n\t\t\"slots\": {\r\n\t\t\t\"co3 mat1\": {\r\n\t\t\t\t\"attachment\": [\r\n\t\t\t\t\t{ \"time\": 0.5, \"name\": null },\r\n\t\t\t\t\t{ \"time\": 0.6, \"name\": \"co3 mat1\" },\r\n\t\t\t\t\t{ \"time\": 0.7, \"name\": null },\r\n\t\t\t\t\t{ \"time\": 0.8, \"name\": \"co3 mat1\" }\r\n\t\t\t\t]\r\n\t\t\t},\r\n\t\t\t\"co3 mat2\": {\r\n\t\t\t\t\"attachment\": [\r\n\t\t\t\t\t{ \"time\": 0.5, \"name\": null },\r\n\t\t\t\t\t{ \"time\": 0.6, \"name\": \"co3 mat2\" },\r\n\t\t\t\t\t{ \"time\": 0.7, \"name\": null },\r\n\t\t\t\t\t{ \"time\": 0.8, \"name\": \"co3 mat2\" }\r\n\t\t\t\t]\r\n\t\t\t},\r\n\t\t\t\"cut\": {\r\n\t\t\t\t\"attachment\": [\r\n\t\t\t\t\t{ \"time\": 0, \"name\": \"cut\" }\r\n\t\t\t\t]\r\n\t\t\t}\r\n\t\t},\r\n\t\t\"bones\": {\r\n\t\t\t\"bone33\": {\r\n\t\t\t\t\"rotate\": [\r\n\t\t\t\t\t{ \"time\": 0, \"angle\": 0, \"curve\": \"stepped\" },\r\n\t\t\t\t\t{ \"time\": 1.3333, \"angle\": 0 }\r\n\t\t\t\t],\r\n\t\t\t\t\"translate\": [\r\n\t\t\t\t\t{ \"time\": 0, \"x\": 0, \"y\": 0, \"curve\": \"stepped\" },\r\n\t\t\t\t\t{ \"time\": 1.3333, \"x\": 0, \"y\": 0 }\r\n\t\t\t\t],\r\n\t\t\t\t\"scale\": [\r\n\t\t\t\t\t{ \"time\": 0, \"x\": 1, \"y\": 1, \"curve\": \"stepped\" },\r\n\t\t\t\t\t{ \"time\": 1.3333, \"x\": 1, \"y\": 1 }\r\n\t\t\t\t]\r\n\t\t\t},\r\n\t\t\t\"bone34\": {\r\n\t\t\t\t\"rotate\": [\r\n\t\t\t\t\t{ \"time\": 0, \"angle\": 0, \"curve\": \"stepped\" },\r\n\t\t\t\t\t{ \"time\": 1.3333, \"angle\": 0 }\r\n\t\t\t\t],\r\n\t\t\t\t\"translate\": [\r\n\t\t\t\t\t{ \"time\": 0, \"x\": 0, \"y\": 0, \"curve\": \"stepped\" },\r\n\t\t\t\t\t{ \"time\": 1.3333, \"x\": 0, \"y\": 0 }\r\n\t\t\t\t],\r\n\t\t\t\t\"scale\": [\r\n\t\t\t\t\t{ \"time\": 0, \"x\": 1, \"y\": 1, \"curve\": \"stepped\" },\r\n\t\t\t\t\t{ \"time\": 1.3333, \"x\": 1, \"y\": 1 }\r\n\t\t\t\t]\r\n\t\t\t},\r\n\t\t\t\"bone28\": {\r\n\t\t\t\t\"rotate\": [\r\n\t\t\t\t\t{ \"time\": 0, \"angle\": 0 }\r\n\t\t\t\t],\r\n\t\t\t\t\"translate\": [\r\n\t\t\t\t\t{ \"time\": 0, \"x\": 0, \"y\": 0 }\r\n\t\t\t\t],\r\n\t\t\t\t\"scale\": [\r\n\t\t\t\t\t{ \"time\": 0, \"x\": 1, \"y\": 1 }\r\n\t\t\t\t]\r\n\t\t\t},\r\n\t\t\t\"bone29\": {\r\n\t\t\t\t\"rotate\": [\r\n\t\t\t\t\t{ \"time\": 0, \"angle\": 0 },\r\n\t\t\t\t\t{ \"time\": 0.3333, \"angle\": 1.28 },\r\n\t\t\t\t\t{ \"time\": 0.6667, \"angle\": 0 },\r\n\t\t\t\t\t{ \"time\": 1, \"angle\": -2.83 },\r\n\t\t\t\t\t{ \"time\": 1.3333, \"angle\": 0 },\r\n\t\t\t\t\t{ \"time\": 1.6667, \"angle\": 1.28 },\r\n\t\t\t\t\t{ \"time\": 2, \"angle\": 0 },\r\n\t\t\t\t\t{ \"time\": 2.3333, \"angle\": -2.83 },\r\n\t\t\t\t\t{ \"time\": 2.6667, \"angle\": 0 }\r\n\t\t\t\t],\r\n\t\t\t\t\"translate\": [\r\n\t\t\t\t\t{ \"time\": 0, \"x\": 0, \"y\": 0, \"curve\": \"stepped\" },\r\n\t\t\t\t\t{ \"time\": 0.6667, \"x\": 0, \"y\": 0 },\r\n\t\t\t\t\t{ \"time\": 1, \"x\": -6.96, \"y\": 0.31 },\r\n\t\t\t\t\t{ \"time\": 1.3333, \"x\": 0, \"y\": 0, \"curve\": \"stepped\" },\r\n\t\t\t\t\t{ \"time\": 2, \"x\": 0, \"y\": 0 },\r\n\t\t\t\t\t{ \"time\": 2.3333, \"x\": -6.96, \"y\": 0.31 },\r\n\t\t\t\t\t{ \"time\": 2.6667, \"x\": 0, \"y\": 0 }\r\n\t\t\t\t],\r\n\t\t\t\t\"scale\": [\r\n\t\t\t\t\t{ \"time\": 0, \"x\": 1, \"y\": 1, \"curve\": \"stepped\" },\r\n\t\t\t\t\t{ \"time\": 0.6667, \"x\": 1, \"y\": 1, \"curve\": \"stepped\" },\r\n\t\t\t\t\t{ \"time\": 1.3333, \"x\": 1, \"y\": 1, \"curve\": \"stepped\" },\r\n\t\t\t\t\t{ \"time\": 2, \"x\": 1, \"y\": 1, \"curve\": \"stepped\" },\r\n\t\t\t\t\t{ \"time\": 2.6667, \"x\": 1, \"y\": 1 }\r\n\t\t\t\t]\r\n\t\t\t},\r\n\t\t\t\"bone30\": {\r\n\t\t\t\t\"rotate\": [\r\n\t\t\t\t\t{ \"time\": 0, \"angle\": 0 },\r\n\t\t\t\t\t{ \"time\": 0.3333, \"angle\": 1.55 },\r\n\t\t\t\t\t{ \"time\": 0.6667, \"angle\": 0 },\r\n\t\t\t\t\t{ \"time\": 1, \"angle\": -2.11 },\r\n\t\t\t\t\t{ \"time\": 1.3333, \"angle\": 0 },\r\n\t\t\t\t\t{ \"time\": 1.8333, \"angle\": 1.55 },\r\n\t\t\t\t\t{ \"time\": 2.2, \"angle\": 0, \"curve\": \"stepped\" },\r\n\t\t\t\t\t{ \"time\": 2.6667, \"angle\": 0 }\r\n\t\t\t\t],\r\n\t\t\t\t\"translate\": [\r\n\t\t\t\t\t{ \"time\": 0, \"x\": 0, \"y\": 0, \"curve\": \"stepped\" },\r\n\t\t\t\t\t{ \"time\": 0.6667, \"x\": 0, \"y\": 0 },\r\n\t\t\t\t\t{ \"time\": 1, \"x\": 1.15, \"y\": 5.72 },\r\n\t\t\t\t\t{ \"time\": 1.3333, \"x\": 0, \"y\": 0, \"curve\": \"stepped\" },\r\n\t\t\t\t\t{ \"time\": 2.2, \"x\": 0, \"y\": 0, \"curve\": \"stepped\" },\r\n\t\t\t\t\t{ \"time\": 2.6667, \"x\": 0, \"y\": 0 }\r\n\t\t\t\t],\r\n\t\t\t\t\"scale\": [\r\n\t\t\t\t\t{ \"time\": 0, \"x\": 1, \"y\": 1, \"curve\": \"stepped\" },\r\n\t\t\t\t\t{ \"time\": 0.6667, \"x\": 1, \"y\": 1, \"curve\": \"stepped\" },\r\n\t\t\t\t\t{ \"time\": 1.3333, \"x\": 1, \"y\": 1, \"curve\": \"stepped\" },\r\n\t\t\t\t\t{ \"time\": 2.2, \"x\": 1, \"y\": 1, \"curve\": \"stepped\" },\r\n\t\t\t\t\t{ \"time\": 2.6667, \"x\": 1, \"y\": 1 }\r\n\t\t\t\t]\r\n\t\t\t},\r\n\t\t\t\"bone31\": {\r\n\t\t\t\t\"rotate\": [\r\n\t\t\t\t\t{ \"time\": 0, \"angle\": 0 },\r\n\t\t\t\t\t{\r\n\t\t\t\t\t\t\"time\": 0.3333,\r\n\t\t\t\t\t\t\"angle\": 0.32,\r\n\t\t\t\t\t\t\"curve\": [ 0.25, 0, 0.75, 1 ]\r\n\t\t\t\t\t},\r\n\t\t\t\t\t{ \"time\": 1, \"angle\": 2.21 },\r\n\t\t\t\t\t{ \"time\": 1.3333, \"angle\": 0 },\r\n\t\t\t\t\t{\r\n\t\t\t\t\t\t\"time\": 1.6667,\r\n\t\t\t\t\t\t\"angle\": 0.32,\r\n\t\t\t\t\t\t\"curve\": [ 0.25, 0, 0.75, 1 ]\r\n\t\t\t\t\t},\r\n\t\t\t\t\t{ \"time\": 2.3333, \"angle\": 2.21 },\r\n\t\t\t\t\t{ \"time\": 2.6667, \"angle\": 0 }\r\n\t\t\t\t],\r\n\t\t\t\t\"translate\": [\r\n\t\t\t\t\t{ \"time\": 0, \"x\": 0, \"y\": 0, \"curve\": \"stepped\" },\r\n\t\t\t\t\t{ \"time\": 1.3333, \"x\": 0, \"y\": 0, \"curve\": \"stepped\" },\r\n\t\t\t\t\t{ \"time\": 2.6667, \"x\": 0, \"y\": 0 }\r\n\t\t\t\t],\r\n\t\t\t\t\"scale\": [\r\n\t\t\t\t\t{ \"time\": 0, \"x\": 1, \"y\": 1, \"curve\": \"stepped\" },\r\n\t\t\t\t\t{ \"time\": 1.3333, \"x\": 1, \"y\": 1, \"curve\": \"stepped\" },\r\n\t\t\t\t\t{ \"time\": 2.6667, \"x\": 1, \"y\": 1 }\r\n\t\t\t\t]\r\n\t\t\t},\r\n\t\t\t\"bone32\": {\r\n\t\t\t\t\"rotate\": [\r\n\t\t\t\t\t{ \"time\": 0, \"angle\": 0 },\r\n\t\t\t\t\t{ \"time\": 1, \"angle\": 1.22 },\r\n\t\t\t\t\t{ \"time\": 1.3333, \"angle\": 0 },\r\n\t\t\t\t\t{ \"time\": 2.3333, \"angle\": 1.22 },\r\n\t\t\t\t\t{ \"time\": 2.6667, \"angle\": 0 }\r\n\t\t\t\t],\r\n\t\t\t\t\"translate\": [\r\n\t\t\t\t\t{ \"time\": 0, \"x\": 0, \"y\": 0 },\r\n\t\t\t\t\t{ \"time\": 1, \"x\": -4.49, \"y\": 2.01 },\r\n\t\t\t\t\t{ \"time\": 1.3333, \"x\": 0, \"y\": 0 },\r\n\t\t\t\t\t{ \"time\": 2.3333, \"x\": -4.49, \"y\": 2.01 },\r\n\t\t\t\t\t{ \"time\": 2.6667, \"x\": 0, \"y\": 0 }\r\n\t\t\t\t],\r\n\t\t\t\t\"scale\": [\r\n\t\t\t\t\t{ \"time\": 0, \"x\": 1, \"y\": 1, \"curve\": \"stepped\" },\r\n\t\t\t\t\t{ \"time\": 1.3333, \"x\": 1, \"y\": 1, \"curve\": \"stepped\" },\r\n\t\t\t\t\t{ \"time\": 2.6667, \"x\": 1, \"y\": 1 }\r\n\t\t\t\t]\r\n\t\t\t},\r\n\t\t\t\"bone35\": {\r\n\t\t\t\t\"rotate\": [\r\n\t\t\t\t\t{ \"time\": 0, \"angle\": 0, \"curve\": \"stepped\" },\r\n\t\t\t\t\t{ \"time\": 0.3333, \"angle\": 0, \"curve\": \"stepped\" },\r\n\t\t\t\t\t{ \"time\": 0.6667, \"angle\": 0, \"curve\": \"stepped\" },\r\n\t\t\t\t\t{ \"time\": 1, \"angle\": 0, \"curve\": \"stepped\" },\r\n\t\t\t\t\t{ \"time\": 1.3333, \"angle\": 0, \"curve\": \"stepped\" },\r\n\t\t\t\t\t{ \"time\": 1.6667, \"angle\": 0, \"curve\": \"stepped\" },\r\n\t\t\t\t\t{ \"time\": 2, \"angle\": 0, \"curve\": \"stepped\" },\r\n\t\t\t\t\t{ \"time\": 2.3333, \"angle\": 0, \"curve\": \"stepped\" },\r\n\t\t\t\t\t{ \"time\": 2.6667, \"angle\": 0 }\r\n\t\t\t\t],\r\n\t\t\t\t\"translate\": [\r\n\t\t\t\t\t{ \"time\": 0, \"x\": 0, \"y\": 0, \"curve\": \"stepped\" },\r\n\t\t\t\t\t{ \"time\": 0.3333, \"x\": 0, \"y\": 0, \"curve\": \"stepped\" },\r\n\t\t\t\t\t{ \"time\": 0.6667, \"x\": 0, \"y\": 0, \"curve\": \"stepped\" },\r\n\t\t\t\t\t{ \"time\": 1, \"x\": 0, \"y\": 0, \"curve\": \"stepped\" },\r\n\t\t\t\t\t{ \"time\": 1.3333, \"x\": 0, \"y\": 0, \"curve\": \"stepped\" },\r\n\t\t\t\t\t{ \"time\": 1.6667, \"x\": 0, \"y\": 0, \"curve\": \"stepped\" },\r\n\t\t\t\t\t{ \"time\": 2, \"x\": 0, \"y\": 0, \"curve\": \"stepped\" },\r\n\t\t\t\t\t{ \"time\": 2.3333, \"x\": 0, \"y\": 0, \"curve\": \"stepped\" },\r\n\t\t\t\t\t{ \"time\": 2.6667, \"x\": 0, \"y\": 0 }\r\n\t\t\t\t],\r\n\t\t\t\t\"scale\": [\r\n\t\t\t\t\t{ \"time\": 0, \"x\": 1, \"y\": 1 },\r\n\t\t\t\t\t{ \"time\": 0.1667, \"x\": 1.271, \"y\": 1.431 },\r\n\t\t\t\t\t{ \"time\": 0.3333, \"x\": 1, \"y\": 1 },\r\n\t\t\t\t\t{ \"time\": 0.5, \"x\": 1.271, \"y\": 1.431 },\r\n\t\t\t\t\t{ \"time\": 0.6667, \"x\": 0.709, \"y\": 0.742 },\r\n\t\t\t\t\t{ \"time\": 0.8333, \"x\": 1.271, \"y\": 1.431 },\r\n\t\t\t\t\t{ \"time\": 1, \"x\": 1, \"y\": 1 },\r\n\t\t\t\t\t{ \"time\": 1.1667, \"x\": 1.271, \"y\": 1.431 },\r\n\t\t\t\t\t{ \"time\": 1.3333, \"x\": 1, \"y\": 1 },\r\n\t\t\t\t\t{ \"time\": 1.5, \"x\": 1.271, \"y\": 1.431 },\r\n\t\t\t\t\t{ \"time\": 1.6667, \"x\": 1, \"y\": 1 },\r\n\t\t\t\t\t{ \"time\": 1.8333, \"x\": 1.271, \"y\": 1.431 },\r\n\t\t\t\t\t{ \"time\": 2, \"x\": 0.709, \"y\": 0.742 },\r\n\t\t\t\t\t{ \"time\": 2.1667, \"x\": 1.271, \"y\": 1.431 },\r\n\t\t\t\t\t{ \"time\": 2.3333, \"x\": 1, \"y\": 1 },\r\n\t\t\t\t\t{ \"time\": 2.5, \"x\": 1.271, \"y\": 1.431 },\r\n\t\t\t\t\t{ \"time\": 2.6667, \"x\": 1, \"y\": 1 }\r\n\t\t\t\t]\r\n\t\t\t},\r\n\t\t\t\"bone37\": {\r\n\t\t\t\t\"rotate\": [\r\n\t\t\t\t\t{ \"time\": 0, \"angle\": 0, \"curve\": \"stepped\" },\r\n\t\t\t\t\t{ \"time\": 0.8667, \"angle\": 0, \"curve\": \"stepped\" },\r\n\t\t\t\t\t{ \"time\": 1.7, \"angle\": 0, \"curve\": \"stepped\" },\r\n\t\t\t\t\t{ \"time\": 2.6667, \"angle\": 0 }\r\n\t\t\t\t],\r\n\t\t\t\t\"translate\": [\r\n\t\t\t\t\t{ \"time\": 0, \"x\": 0, \"y\": 0, \"curve\": \"stepped\" },\r\n\t\t\t\t\t{ \"time\": 0.8667, \"x\": 0, \"y\": 0, \"curve\": \"stepped\" },\r\n\t\t\t\t\t{ \"time\": 1.7, \"x\": 0, \"y\": 0, \"curve\": \"stepped\" },\r\n\t\t\t\t\t{ \"time\": 2.6667, \"x\": 0, \"y\": 0 }\r\n\t\t\t\t],\r\n\t\t\t\t\"scale\": [\r\n\t\t\t\t\t{ \"time\": 0, \"x\": 1, \"y\": 1 },\r\n\t\t\t\t\t{ \"time\": 0.3333, \"x\": 1.272, \"y\": 1.18 },\r\n\t\t\t\t\t{ \"time\": 0.8667, \"x\": 1, \"y\": 1 },\r\n\t\t\t\t\t{ \"time\": 1.2667, \"x\": 1.272, \"y\": 1.18 },\r\n\t\t\t\t\t{ \"time\": 1.7, \"x\": 1, \"y\": 1 },\r\n\t\t\t\t\t{ \"time\": 2.2, \"x\": 1.272, \"y\": 1.18 },\r\n\t\t\t\t\t{ \"time\": 2.6667, \"x\": 1, \"y\": 1 }\r\n\t\t\t\t]\r\n\t\t\t}\r\n\t\t}\r\n\t}\r\n}\r\n}","_skeletonJson":{"skeleton":{"hash":"ylgk/0WvXHjNdESHLRJqUtGulxI","spine":"3.6.52","width":377.01,"height":553,"images":"./images/cowboy cmc/"},"bones":[{"name":"root"},{"name":"bone","parent":"root","x":33.09,"y":163.96},{"name":"bone2","parent":"bone","length":134.98,"rotation":89.04,"x":-5.28,"y":36.83},{"name":"bone3","parent":"bone2","length":79.17,"rotation":0.41,"x":134.98},{"name":"bone4","parent":"bone3","length":175.24,"rotation":0.55,"x":78.81,"y":-1.05},{"name":"bone5","parent":"bone4","length":62.57,"rotation":164.98,"x":159.07,"y":32.16},{"name":"bone6","parent":"bone4","length":60.92,"rotation":-145.35,"x":77.26,"y":-49.65},{"name":"bone7","parent":"bone4","length":61,"rotation":171.67,"x":42.28,"y":46.33},{"name":"bone8","parent":"bone3","x":2.78,"y":-1.31},{"name":"bone9","parent":"bone4","x":93.22,"y":-39.79},{"name":"bone10","parent":"bone4","x":133.48,"y":7.26},{"name":"bone11","parent":"bone4","x":144.63,"y":-36.88},{"name":"bone12","parent":"bone3","length":91.67,"rotation":160.22,"x":35.73,"y":89.9},{"name":"bone13","parent":"bone","length":74.46,"rotation":91.97,"x":-17.51,"y":476.98},{"name":"bone14","parent":"root","x":29.99,"y":166.11},{"name":"bone15","parent":"bone14","length":123.76,"rotation":90.41,"x":12.6,"y":20.45},{"name":"bone16","parent":"bone15","length":144.41,"rotation":-7.8,"x":123.76},{"name":"bone17","parent":"bone16","length":141.52,"rotation":11.35,"x":143.09,"y":-1.01},{"name":"bone18","parent":"bone16","x":32.44,"y":11.42},{"name":"bone19","parent":"bone16","length":203.68,"rotation":156.39,"x":93.1,"y":49.9},{"name":"bone20","parent":"bone19","length":206.98,"rotation":-149.2,"x":207.9,"y":-7.07},{"name":"bone21","parent":"bone17","length":43.99,"rotation":88.68,"x":184.4,"y":1.42},{"name":"bone22","parent":"bone21","length":31.78,"rotation":26.65,"x":43.99},{"name":"bone23","parent":"bone22","length":28.72,"rotation":34.14,"x":31.78},{"name":"bone24","parent":"bone23","length":36.53,"rotation":24.44,"x":28.72},{"name":"bone25","parent":"bone17","x":80.83,"y":32.31},{"name":"bone26","parent":"bone17","x":78.56,"y":-10.23},{"name":"bone27","parent":"bone17","x":31.11,"y":18.81},{"name":"bone28","parent":"bone14","x":3.3,"y":-4.63},{"name":"bone29","parent":"bone28","length":212.35,"rotation":90,"x":-54.74,"y":25.56},{"name":"bone30","parent":"bone29","length":260.85,"rotation":-122.01,"x":179.17,"y":67.47},{"name":"bone31","parent":"bone30","length":253.36,"rotation":123.51,"x":253.58,"y":3.28},{"name":"bone32","parent":"bone29","length":209.66,"rotation":-2.65,"x":233.48,"y":0.67},{"name":"bone33","parent":"bone32","x":131.42,"y":-27.56},{"name":"bone34","parent":"bone33","x":-6.29,"y":-49.68},{"name":"bone35","parent":"bone32","x":73.2,"y":-22.37},{"name":"bone36","parent":"bone14","length":94.59,"rotation":90,"x":-19.62,"y":477.14},{"name":"bone37","parent":"bone28","length":68.17,"rotation":91.17,"x":-4.32,"y":477.59}],"slots":[{"name":"cut","bone":"root","attachment":"cut"},{"name":"co3 cowboy","bone":"bone28","attachment":"co3 cowboy"},{"name":"co3 body","bone":"bone29","attachment":"co3 body"},{"name":"co3 head","bone":"bone32","attachment":"co3 head"},{"name":"co3 mat2","bone":"bone34","attachment":"co3 mat2"},{"name":"co3 mat1","bone":"bone33","attachment":"co3 mat1"},{"name":"co3 omlua","bone":"bone35","attachment":"co3 omlua"},{"name":"co3 tay1","bone":"bone30","attachment":"co3 tay1"},{"name":"co3 tay2","bone":"bone31","attachment":"co3 tay2"},{"name":"co3 Layer 2 copy 3","bone":"bone28","attachment":"co3 Layer 2 copy 3"},{"name":"co3 shape","bone":"bone28","attachment":"co3 shape"},{"name":"co3 COWBOY 3","bone":"bone37","attachment":"co3 COWBOY 3"}],"skins":{"default":{"co3 COWBOY 3":{"co3 COWBOY 3":{"x":35.32,"y":-6.66,"rotation":-91.17,"width":197,"height":80}},"co3 Layer 2 copy 3":{"co3 Layer 2 copy 3":{"x":-2.88,"y":291.54,"width":318,"height":553}},"co3 body":{"co3 body":{"x":161.48,"y":-5.85,"rotation":-90,"width":336,"height":322}},"co3 cowboy":{"co3 cowboy":{"x":1.12,"y":300.54,"width":318,"height":529}},"co3 head":{"co3 head":{"x":105.42,"y":-39.2,"rotation":-87.35,"width":289,"height":267}},"co3 mat1":{"co3 mat1":{"x":-0.55,"y":1.04,"rotation":-87.35,"width":38,"height":21}},"co3 mat2":{"co3 mat2":{"x":3.06,"y":0.54,"rotation":-87.35,"width":24,"height":19}},"co3 omlua":{"co3 omlua":{"x":-1.14,"y":1.15,"rotation":-87.35,"width":12,"height":12}},"co3 shape":{"co3 shape":{"x":1.12,"y":133.54,"width":220,"height":77}},"co3 tay1":{"co3 tay1":{"x":119.94,"y":8.7,"rotation":32.01,"width":264,"height":225}},"co3 tay2":{"co3 tay2":{"x":187.2,"y":8.06,"rotation":-91.5,"width":111,"height":424}},"cut":{"cut":{"type":"clipping","end":"co3 tay2","vertexCount":8,"vertices":[-92.79,203.54,123.84,203.36,157.39,229.59,157.2,679.76,130.06,705.46,-96.85,705.82,-113.3,682.8,-115.76,237.44],"color":"ce3a3aff"}}}},"animations":{"co3":{"slots":{"co3 mat1":{"attachment":[{"time":0.5,"name":null},{"time":0.6,"name":"co3 mat1"},{"time":0.7,"name":null},{"time":0.8,"name":"co3 mat1"}]},"co3 mat2":{"attachment":[{"time":0.5,"name":null},{"time":0.6,"name":"co3 mat2"},{"time":0.7,"name":null},{"time":0.8,"name":"co3 mat2"}]},"cut":{"attachment":[{"time":0,"name":"cut"}]}},"bones":{"bone33":{"rotate":[{"time":0,"angle":0,"curve":"stepped"},{"time":1.3333,"angle":0}],"translate":[{"time":0,"x":0,"y":0,"curve":"stepped"},{"time":1.3333,"x":0,"y":0}],"scale":[{"time":0,"x":1,"y":1,"curve":"stepped"},{"time":1.3333,"x":1,"y":1}]},"bone34":{"rotate":[{"time":0,"angle":0,"curve":"stepped"},{"time":1.3333,"angle":0}],"translate":[{"time":0,"x":0,"y":0,"curve":"stepped"},{"time":1.3333,"x":0,"y":0}],"scale":[{"time":0,"x":1,"y":1,"curve":"stepped"},{"time":1.3333,"x":1,"y":1}]},"bone28":{"rotate":[{"time":0,"angle":0}],"translate":[{"time":0,"x":0,"y":0}],"scale":[{"time":0,"x":1,"y":1}]},"bone29":{"rotate":[{"time":0,"angle":0},{"time":0.3333,"angle":1.28},{"time":0.6667,"angle":0},{"time":1,"angle":-2.83},{"time":1.3333,"angle":0},{"time":1.6667,"angle":1.28},{"time":2,"angle":0},{"time":2.3333,"angle":-2.83},{"time":2.6667,"angle":0}],"translate":[{"time":0,"x":0,"y":0,"curve":"stepped"},{"time":0.6667,"x":0,"y":0},{"time":1,"x":-6.96,"y":0.31},{"time":1.3333,"x":0,"y":0,"curve":"stepped"},{"time":2,"x":0,"y":0},{"time":2.3333,"x":-6.96,"y":0.31},{"time":2.6667,"x":0,"y":0}],"scale":[{"time":0,"x":1,"y":1,"curve":"stepped"},{"time":0.6667,"x":1,"y":1,"curve":"stepped"},{"time":1.3333,"x":1,"y":1,"curve":"stepped"},{"time":2,"x":1,"y":1,"curve":"stepped"},{"time":2.6667,"x":1,"y":1}]},"bone30":{"rotate":[{"time":0,"angle":0},{"time":0.3333,"angle":1.55},{"time":0.6667,"angle":0},{"time":1,"angle":-2.11},{"time":1.3333,"angle":0},{"time":1.8333,"angle":1.55},{"time":2.2,"angle":0,"curve":"stepped"},{"time":2.6667,"angle":0}],"translate":[{"time":0,"x":0,"y":0,"curve":"stepped"},{"time":0.6667,"x":0,"y":0},{"time":1,"x":1.15,"y":5.72},{"time":1.3333,"x":0,"y":0,"curve":"stepped"},{"time":2.2,"x":0,"y":0,"curve":"stepped"},{"time":2.6667,"x":0,"y":0}],"scale":[{"time":0,"x":1,"y":1,"curve":"stepped"},{"time":0.6667,"x":1,"y":1,"curve":"stepped"},{"time":1.3333,"x":1,"y":1,"curve":"stepped"},{"time":2.2,"x":1,"y":1,"curve":"stepped"},{"time":2.6667,"x":1,"y":1}]},"bone31":{"rotate":[{"time":0,"angle":0},{"time":0.3333,"angle":0.32,"curve":[0.25,0,0.75,1]},{"time":1,"angle":2.21},{"time":1.3333,"angle":0},{"time":1.6667,"angle":0.32,"curve":[0.25,0,0.75,1]},{"time":2.3333,"angle":2.21},{"time":2.6667,"angle":0}],"translate":[{"time":0,"x":0,"y":0,"curve":"stepped"},{"time":1.3333,"x":0,"y":0,"curve":"stepped"},{"time":2.6667,"x":0,"y":0}],"scale":[{"time":0,"x":1,"y":1,"curve":"stepped"},{"time":1.3333,"x":1,"y":1,"curve":"stepped"},{"time":2.6667,"x":1,"y":1}]},"bone32":{"rotate":[{"time":0,"angle":0},{"time":1,"angle":1.22},{"time":1.3333,"angle":0},{"time":2.3333,"angle":1.22},{"time":2.6667,"angle":0}],"translate":[{"time":0,"x":0,"y":0},{"time":1,"x":-4.49,"y":2.01},{"time":1.3333,"x":0,"y":0},{"time":2.3333,"x":-4.49,"y":2.01},{"time":2.6667,"x":0,"y":0}],"scale":[{"time":0,"x":1,"y":1,"curve":"stepped"},{"time":1.3333,"x":1,"y":1,"curve":"stepped"},{"time":2.6667,"x":1,"y":1}]},"bone35":{"rotate":[{"time":0,"angle":0,"curve":"stepped"},{"time":0.3333,"angle":0,"curve":"stepped"},{"time":0.6667,"angle":0,"curve":"stepped"},{"time":1,"angle":0,"curve":"stepped"},{"time":1.3333,"angle":0,"curve":"stepped"},{"time":1.6667,"angle":0,"curve":"stepped"},{"time":2,"angle":0,"curve":"stepped"},{"time":2.3333,"angle":0,"curve":"stepped"},{"time":2.6667,"angle":0}],"translate":[{"time":0,"x":0,"y":0,"curve":"stepped"},{"time":0.3333,"x":0,"y":0,"curve":"stepped"},{"time":0.6667,"x":0,"y":0,"curve":"stepped"},{"time":1,"x":0,"y":0,"curve":"stepped"},{"time":1.3333,"x":0,"y":0,"curve":"stepped"},{"time":1.6667,"x":0,"y":0,"curve":"stepped"},{"time":2,"x":0,"y":0,"curve":"stepped"},{"time":2.3333,"x":0,"y":0,"curve":"stepped"},{"time":2.6667,"x":0,"y":0}],"scale":[{"time":0,"x":1,"y":1},{"time":0.1667,"x":1.271,"y":1.431},{"time":0.3333,"x":1,"y":1},{"time":0.5,"x":1.271,"y":1.431},{"time":0.6667,"x":0.709,"y":0.742},{"time":0.8333,"x":1.271,"y":1.431},{"time":1,"x":1,"y":1},{"time":1.1667,"x":1.271,"y":1.431},{"time":1.3333,"x":1,"y":1},{"time":1.5,"x":1.271,"y":1.431},{"time":1.6667,"x":1,"y":1},{"time":1.8333,"x":1.271,"y":1.431},{"time":2,"x":0.709,"y":0.742},{"time":2.1667,"x":1.271,"y":1.431},{"time":2.3333,"x":1,"y":1},{"time":2.5,"x":1.271,"y":1.431},{"time":2.6667,"x":1,"y":1}]},"bone37":{"rotate":[{"time":0,"angle":0,"curve":"stepped"},{"time":0.8667,"angle":0,"curve":"stepped"},{"time":1.7,"angle":0,"curve":"stepped"},{"time":2.6667,"angle":0}],"translate":[{"time":0,"x":0,"y":0,"curve":"stepped"},{"time":0.8667,"x":0,"y":0,"curve":"stepped"},{"time":1.7,"x":0,"y":0,"curve":"stepped"},{"time":2.6667,"x":0,"y":0}],"scale":[{"time":0,"x":1,"y":1},{"time":0.3333,"x":1.272,"y":1.18},{"time":0.8667,"x":1,"y":1},{"time":1.2667,"x":1.272,"y":1.18},{"time":1.7,"x":1,"y":1},{"time":2.2,"x":1.272,"y":1.18},{"time":2.6667,"x":1,"y":1}]}}}}},"_atlasText":"\r\ncowboy cmc3.png\r\nsize: 2048,512\r\nformat: RGBA8888\r\nfilter: Linear,Linear\r\nrepeat: none\r\nco3 COWBOY 3\r\n  rotate: false\r\n  xy: 650, 54\r\n  size: 197, 80\r\n  orig: 197, 80\r\n  offset: 0, 0\r\n  index: -1\r\nco3 Layer 2 copy 3\r\n  rotate: true\r\n  xy: 2, 136\r\n  size: 318, 553\r\n  orig: 318, 553\r\n  offset: 0, 0\r\n  index: -1\r\nco3 body\r\n  rotate: false\r\n  xy: 1088, 132\r\n  size: 336, 322\r\n  orig: 336, 322\r\n  offset: 0, 0\r\n  index: -1\r\nco3 cowboy\r\n  rotate: true\r\n  xy: 557, 136\r\n  size: 318, 529\r\n  orig: 318, 529\r\n  offset: 0, 0\r\n  index: -1\r\nco3 head\r\n  rotate: false\r\n  xy: 1426, 187\r\n  size: 289, 267\r\n  orig: 289, 267\r\n  offset: 0, 0\r\n  index: -1\r\nco3 mat1\r\n  rotate: false\r\n  xy: 1426, 164\r\n  size: 38, 21\r\n  orig: 38, 21\r\n  offset: 0, 0\r\n  index: -1\r\nco3 mat2\r\n  rotate: false\r\n  xy: 2, 2\r\n  size: 24, 19\r\n  orig: 24, 19\r\n  offset: 0, 0\r\n  index: -1\r\nco3 omlua\r\n  rotate: false\r\n  xy: 1717, 215\r\n  size: 12, 12\r\n  orig: 12, 12\r\n  offset: 0, 0\r\n  index: -1\r\nco3 shape\r\n  rotate: false\r\n  xy: 428, 57\r\n  size: 220, 77\r\n  orig: 220, 77\r\n  offset: 0, 0\r\n  index: -1\r\nco3 tay1\r\n  rotate: false\r\n  xy: 1717, 229\r\n  size: 264, 225\r\n  orig: 264, 225\r\n  offset: 0, 0\r\n  index: -1\r\nco3 tay2\r\n  rotate: true\r\n  xy: 2, 23\r\n  size: 111, 424\r\n  orig: 111, 424\r\n  offset: 0, 0\r\n  index: -1\r\n","textures":[{"__uuid__":"5dhKy99HlBh5dxcxRkHOBr"}],"textureNames":["cowboy cmc3.png"]}